wbsearch/__init__.py
wbsearch/wbsearch.py
wbsearch-2.3.1.dist-info/METADATA
wbsearch-2.3.1.dist-info/WHEEL
wbsearch-2.3.1.dist-info/entry_points.txt
wbsearch-2.3.1.dist-info/top_level.txt
wbsearch-2.3.1.dist-info/RECORD
