Metadata-Version: 2.1
Name: wbsearch
Version: 2.3.1
Summary: Search anything on main browser directly from terminal
Author: Cargo
Author-email: cargo.coder@gmail.com
License: UNKNOWN
Platform: UNKNOWN
Requires-Dist: click
Requires-Dist: kvk
